markdownlit/__init__.py
markdownlit/extensions/align.py
markdownlit/extensions/arrow.py
markdownlit/extensions/at_sign.py
markdownlit/extensions/color.py
markdownlit/extensions/double_dash.py
markdownlit-0.0.7.dist-info/LICENSE
markdownlit-0.0.7.dist-info/METADATA
markdownlit-0.0.7.dist-info/WHEEL
markdownlit-0.0.7.dist-info/top_level.txt
markdownlit-0.0.7.dist-info/RECORD
