Metadata-Version: 2.1
Name: markdownlit
Version: 0.0.7
Summary: markdownlit adds a couple of lit Markdown capabilities to your Streamlit apps
Author-email: Arnaud Miribel <arnaudmiribel@gmail.com>
License:                                  Apache License
Project-URL: Homepage, https://github.com/arnaudmiribel/markdownlit
Project-URL: Bug Tracker, https://github.com/arnaudmiribel/markdownlit/issues
Keywords: python,streamlit,markdown
Classifier: Programming Language :: Python :: 3
Requires-Python: >=3.6
License-File: LICENSE
